{"filter":false,"title":"api_spec.json","tooltip":"/ib_miniprojects_backend/project_management_portal_auth/api_specs/api_spec.json","undoManager":{"mark":1,"position":1,"stack":[[{"start":{"row":0,"column":0},"end":{"row":211,"column":4},"action":"remove","lines":["{","        \"swagger\": \"2.0\",","        \"host\": \"127.0.0.1:8000\",","        \"basePath\": \"/api/fb_post_auth/\",","        \"info\": {","            \"version\": \"1.0.0\",","            \"title\": \"Simple API\",","            \"description\": \"A simple API to learn how to write OpenAPI Specification\"","        },","        \"schemes\": [","            \"http\"","        ],","        \"consumes\": [","            \"application/json\"","        ],","        \"produces\": [","            \"application/json\"","        ],","        \"securityDefinitions\": {","            \"oauth\": {","                \"tokenUrl\": \"http://auth.ibtspl.com/oauth2/\",","                \"flow\": \"password\",","                \"scopes\": {","                    \"read\": \"read users\",","                    \"write\": \"create users\",","                    \"update\": \"update users\",","                    \"delete\": \"delete users\"","                },","                \"type\": \"oauth2\"","            }","        },","        \"security\": [],","        \"definitions\": {","            \"TodoId\": {","                \"type\": \"object\",","                \"properties\": {","                    \"id\": {","                        \"type\": \"integer\"","                    }","                }","            },","            \"BasicTodo\": {","                \"type\": \"object\",","                \"properties\": {","                    \"description\": {","                        \"type\": \"string\"","                    },","                    \"is_completed\": {","                        \"type\": \"boolean\"","                    },","                    \"remind_at\": {","                        \"type\": \"string\"","                    }","                },","                \"required\": [","                    \"description\"","                ]","            },","            \"Todo\": {","                \"allOf\": [","                    {","                        \"$ref\": \"#/definitions/BasicTodo\"","                    },","                    {","                        \"$ref\": \"#/definitions/TodoId\"","                    }","                ]","            }","        },","        \"parameters\": {","            \"TodoId\": {","                \"description\": \"todo id\",","                \"in\": \"path\",","                \"name\": \"id\",","                \"required\": true,","                \"type\": \"integer\"","            },","            \"BasicTodo\": {","                \"description\": \"Todo Parameter\",","                \"in\": \"body\",","                \"name\": \"todo\",","                \"required\": true,","                \"schema\": {","                    \"$ref\": \"#/definitions/BasicTodo\"","                }","            }","        },","        \"responses\": {","            \"SuccessResponse\": {","                \"description\": \"success response\"","            }","        },","        \"paths\": {","            \"/todos/\": {","                \"get\": {","                    \"summary\": \"Get all todos\",","                    \"description\": \"Returns a list containing all todos.\",","                    \"operationId\": \"get_todos\",","                    \"security\": [","                        {","                            \"oauth\": [","                                \"read\"","                            ]","                        }","                    ],","                    \"responses\": {","                        \"200\": {","                            \"description\": \"A list of todos\",","                            \"schema\": {","                                \"type\": \"array\",","                                \"items\": {","                                    \"$ref\": \"#/definitions/Todo\"","                                }","                            }","                        }","                    }","                },","                \"post\": {","                    \"summary\": \"create a todo\",","                    \"description\": \"Create a todo\",","                    \"operationId\": \"create_todo\",","                    \"security\": [","                        {","                            \"oauth\": [","                                \"write\"","                            ]","                        }","                    ],","                    \"parameters\": [","                        {","                            \"$ref\": \"#/parameters/BasicTodo\"","                        }","                    ],","                    \"responses\": {","                        \"200\": {","                            \"description\": \"create a todo\",","                            \"schema\": {","                                \"$ref\": \"#/definitions/TodoId\"","                            }","                        }","                    }","                }","            },","            \"/todos/{id}/\": {","                \"parameters\": [","                    {","                        \"$ref\": \"#/parameters/TodoId\"","                    }","                ],","                \"get\": {","                    \"summary\": \"Get a todo\",","                    \"description\": \"Returns a todo.\",","                    \"operationId\": \"get_todo\",","                    \"security\": [","                        {","                            \"oauth\": [","                                \"read\"","                            ]","                        }","                    ],","                    \"responses\": {","                        \"200\": {","                            \"description\": \"A todo\",","                            \"schema\": {","                                \"$ref\": \"#/definitions/Todo\"","                            }","                        }","                    }","                },","                \"put\": {","                    \"parameters\": [","                        {","                            \"$ref\": \"#/parameters/BasicTodo\"","                        }","                    ],","                    \"summary\": \"Updates a todo\",","                    \"description\": \"Updates a todo.\",","                    \"operationId\": \"update_todo\",","                    \"security\": [","                        {","                            \"oauth\": [","                                \"update\"","                            ]","                        }","                    ],","                    \"responses\": {","                        \"200\": {","                            \"$ref\": \"#/responses/SuccessResponse\"","                        }","                    }","                },","                \"delete\": {","                    \"summary\": \"Deletes a todo\",","                    \"description\": \"Deletes a todo.\",","                    \"operationId\": \"delete_todo\",","                    \"security\": [","                        {","                            \"oauth\": [","                                \"delete\"","                            ]","                        }","                    ],","                    \"responses\": {","                        \"200\": {","                            \"$ref\": \"#/responses/SuccessResponse\"","                        }","                    }","                }","            }","        }","    }","    "],"id":2},{"start":{"row":0,"column":0},"end":{"row":102,"column":0},"action":"insert","lines":["{","    \"swagger\": \"2.0\",","    \"host\": \"localhost:8080\",","    \"basePath\": \"/api/project_management_portal_auth/\",","    \"info\": {","        \"version\": \"1.0.0\",","        \"title\": \"Project Management Platform Auth\",","        \"description\": \"A simple API to know the details of users\"","    },","    \"schemes\": [","        \"https\",","        \"http\"","    ],","    \"consumes\": [","        \"application/json\"","    ],","    \"produces\": [","        \"application/json\"","    ],","    \"securityDefinitions\": {","        \"oauth\": {","            \"tokenUrl\": \"http://auth.ibtspl.com/oauth2/\",","            \"flow\": \"password\",","            \"scopes\": {","                \"read\": \"read users\",","                \"write\": \"create users\",","                \"update\": \"update users\",","                \"delete\": \"delete users\"","            },","            \"type\": \"oauth2\"","        }","    },","    \"definitions\": {},","    \"parameters\": {","        \"UserLoginParameters\": {","            \"name\": \"user_login_details\",","            \"in\": \"body\",","            \"description\": \"user login\",","            \"schema\": {","                \"type\": \"object\",","                \"properties\": {","                    \"username\": {","                        \"type\": \"string\"","                    },","                    \"password\": {","                        \"type\": \"string\"","                    }","                },","                \"required\": [","                    \"username\",","                    \"password\"","                ]","            }","        }","    },","    \"responses\": {","        \"UserLoginResponse\": {","            \"description\": \"user logged in successfully\",","            \"schema\": {","                \"type\": \"object\",","                \"properties\": {","                    \"access_token\": {","                        \"type\": \"string\"","                    },","                    \"refresh_token\": {","                        \"type\": \"string\"","                    },","                    \"is_admin\": {","                        \"type\": \"boolean\"","                    }","                },","                \"required\": [","                    \"access_token\"","                ]","            }","        }","    },","    \"paths\": {","        \"/login/v1/\": {","            \"post\": {","                \"operationId\": \"user_login\",","                \"summary\": \"user login\",","                \"description\": \"login by user\",","                \"parameters\": [{","                    \"$ref\": \"#/parameters/UserLoginParameters\"","                }],","                \"responses\": {","                    \"200\": {","                        \"$ref\": \"#/responses/UserLoginResponse\"","                    },","                    \"400\": {","                        \"description\": \"user not registered\"","                    },","                    \"401\": {","                        \"description\": \"invalid credentials\"","                    }","                }","            }","        }","    }","}","",""]}],[{"start":{"row":101,"column":0},"end":{"row":102,"column":0},"action":"remove","lines":["",""],"id":3}]]},"ace":{"folds":[],"scrolltop":0,"scrollleft":0,"selection":{"start":{"row":101,"column":0},"end":{"row":101,"column":0},"isBackwards":false},"options":{"guessTabSize":true,"useWrapMode":false,"wrapToView":true},"firstLineState":0},"timestamp":1593423034744,"hash":"2149db4a3a787f35556ed8cf790fdfedee191f8b"}